<?xml version="1.0" encoding="UTF-8"?>

<!-- generated on 2026-03-13 13:04:39.744083 by Eclipse SUMO randomTrips.py v1_26_0+0000-fa7df22d7f1
<configuration>
    <net-file value="manhattan.net.xml"/>
    <output-trip-file value="trips_truck.xml"/>
    <prefix value="truck_"/>
    <vehicle-class value="truck"/>
    <fringe-factor value="5"/>
    <period value="20.0"/>
</configuration>
-->

<routes xmlns:xsi="http://www.w3.org/2001/XMLSchema-instance" xsi:noNamespaceSchemaLocation="http://sumo.dlr.de/xsd/routes_file.xsd">
    <vType id="truck__truck" vClass="truck"/>
    <trip id="truck_0" depart="0.00" from="46482609#0" to="-1413518739#1" type="truck__truck"/>
    <trip id="truck_1" depart="20.00" from="1413159922#0" to="127693103#3" type="truck__truck"/>
    <trip id="truck_2" depart="40.00" from="542257982#0" to="542258060#0" type="truck__truck"/>
    <trip id="truck_3" depart="60.00" from="569345540#0" to="1027189507#0" type="truck__truck"/>
    <trip id="truck_4" depart="80.00" from="226041027#0" to="-1413518739#1" type="truck__truck"/>
    <trip id="truck_5" depart="100.00" from="1198594029#0" to="438397345#0" type="truck__truck"/>
    <trip id="truck_6" depart="120.00" from="-1320290376#1" to="1207834766#0" type="truck__truck"/>
    <trip id="truck_7" depart="140.00" from="46482609#0" to="452322757#0" type="truck__truck"/>
    <trip id="truck_8" depart="160.00" from="1198594029#0" to="464516471#9" type="truck__truck"/>
    <trip id="truck_9" depart="180.00" from="5672464#0" to="-1321771943#1" type="truck__truck"/>
    <trip id="truck_10" depart="200.00" from="5672464#0" to="5670225#0" type="truck__truck"/>
    <trip id="truck_11" depart="220.00" from="167922072#0" to="1117867038#0" type="truck__truck"/>
    <trip id="truck_12" depart="240.00" from="846142552#0" to="167922073#0" type="truck__truck"/>
    <trip id="truck_13" depart="260.00" from="1027189508#0" to="1049845754#0" type="truck__truck"/>
    <trip id="truck_14" depart="280.00" from="5672464#0" to="5670867#0" type="truck__truck"/>
    <trip id="truck_15" depart="300.00" from="194926854#0" to="458180183#0" type="truck__truck"/>
    <trip id="truck_16" depart="320.00" from="505317789" to="-167922076#2" type="truck__truck"/>
    <trip id="truck_17" depart="340.00" from="1198594030#0" to="1321771943#0" type="truck__truck"/>
    <trip id="truck_18" depart="360.00" from="-525729008#5" to="1320234484#0" type="truck__truck"/>
    <trip id="truck_19" depart="380.00" from="1031879418#0" to="1320290376#0" type="truck__truck"/>
    <trip id="truck_20" depart="400.00" from="464516471#9" to="194926847#0" type="truck__truck"/>
    <trip id="truck_21" depart="420.00" from="194926854#0" to="125479721#0" type="truck__truck"/>
    <trip id="truck_22" depart="440.00" from="1321771943#0" to="803047267#0" type="truck__truck"/>
    <trip id="truck_23" depart="460.00" from="1106482765#0" to="5670867#0" type="truck__truck"/>
    <trip id="truck_24" depart="480.00" from="1106482765#0" to="194926847#0" type="truck__truck"/>
    <trip id="truck_25" depart="500.00" from="452322757#0" to="542259076#0" type="truck__truck"/>
    <trip id="truck_26" depart="520.00" from="5673323#0" to="5672036#0" type="truck__truck"/>
    <trip id="truck_27" depart="540.00" from="1207834766#0" to="-1413518739#1" type="truck__truck"/>
    <trip id="truck_28" depart="560.00" from="167922072#0" to="1320290376#0" type="truck__truck"/>
    <trip id="truck_29" depart="580.00" from="1198594027#0" to="803047267#0" type="truck__truck"/>
    <trip id="truck_30" depart="600.00" from="569345540#0" to="1413518738" type="truck__truck"/>
    <trip id="truck_31" depart="620.00" from="46482609#0" to="195743210" type="truck__truck"/>
    <trip id="truck_32" depart="640.00" from="626514137#0" to="384178816#3" type="truck__truck"/>
    <trip id="truck_33" depart="660.00" from="1320234484#0" to="1320234484#3" type="truck__truck"/>
    <trip id="truck_34" depart="680.00" from="452322757#3" to="1320290376#0" type="truck__truck"/>
    <trip id="truck_35" depart="700.00" from="458177130#0" to="682360554#0" type="truck__truck"/>
    <trip id="truck_36" depart="720.00" from="195743209#0" to="127693103#0" type="truck__truck"/>
    <trip id="truck_37" depart="740.00" from="968513231#0" to="452322756#0" type="truck__truck"/>
    <trip id="truck_38" depart="760.00" from="1027189507#0" to="-167922076#2" type="truck__truck"/>
    <trip id="truck_39" depart="780.00" from="5670124" to="195743344#0" type="truck__truck"/>
    <trip id="truck_40" depart="800.00" from="-1413518738" to="194926851#0" type="truck__truck"/>
    <trip id="truck_41" depart="820.00" from="968513231#0" to="452322756#4" type="truck__truck"/>
    <trip id="truck_42" depart="840.00" from="846142552#0" to="569345544#0" type="truck__truck"/>
    <trip id="truck_43" depart="860.00" from="-1320290376#1" to="5670867#0" type="truck__truck"/>
    <trip id="truck_44" depart="880.00" from="1321771943#0" to="525729008#0" type="truck__truck"/>
    <trip id="truck_45" depart="900.00" from="1031879418#0" to="226041027#0" type="truck__truck"/>
    <trip id="truck_46" depart="920.00" from="384178816#0" to="803047267#0" type="truck__truck"/>
    <trip id="truck_47" depart="940.00" from="569345540#0" to="1320290376#0" type="truck__truck"/>
    <trip id="truck_48" depart="960.00" from="420907908#0" to="1198594027#0" type="truck__truck"/>
    <trip id="truck_49" depart="980.00" from="569345544#0" to="569345545#0" type="truck__truck"/>
    <trip id="truck_50" depart="1000.00" from="1413518739#0" to="511699175#0" type="truck__truck"/>
    <trip id="truck_51" depart="1020.00" from="464516471#13" to="1117867028" type="truck__truck"/>
    <trip id="truck_52" depart="1040.00" from="5670114#0" to="452322756#4" type="truck__truck"/>
    <trip id="truck_53" depart="1060.00" from="5670114#0" to="452322756#4" type="truck__truck"/>
    <trip id="truck_54" depart="1080.00" from="-1136952921#1" to="167922070#0" type="truck__truck"/>
    <trip id="truck_55" depart="1100.00" from="-1320290376#1" to="803047266#0" type="truck__truck"/>
    <trip id="truck_56" depart="1120.00" from="569345540#0" to="569345538#0" type="truck__truck"/>
    <trip id="truck_57" depart="1140.00" from="167922070#0" to="-542259076#2" type="truck__truck"/>
    <trip id="truck_58" depart="1160.00" from="569345540#0" to="803047267#0" type="truck__truck"/>
    <trip id="truck_59" depart="1180.00" from="-542259076#2" to="438397345#0" type="truck__truck"/>
    <trip id="truck_60" depart="1200.00" from="-167922072#1" to="5671629#0" type="truck__truck"/>
    <trip id="truck_61" depart="1220.00" from="5670114#0" to="1051846230#0" type="truck__truck"/>
    <trip id="truck_62" depart="1240.00" from="397795463#0" to="452322757#3" type="truck__truck"/>
    <trip id="truck_63" depart="1260.00" from="1320234484#0" to="569345545#0" type="truck__truck"/>
    <trip id="truck_64" depart="1280.00" from="226041027#0" to="125480075#0" type="truck__truck"/>
    <trip id="truck_65" depart="1300.00" from="420908138#0" to="5670867#0" type="truck__truck"/>
    <trip id="truck_66" depart="1320.00" from="1198594026#0" to="1413518738" type="truck__truck"/>
    <trip id="truck_67" depart="1340.00" from="35027229#0" to="452322756#4" type="truck__truck"/>
    <trip id="truck_68" depart="1360.00" from="1031879418#0" to="127693103#3" type="truck__truck"/>
    <trip id="truck_69" depart="1380.00" from="167922072#0" to="464516471#9" type="truck__truck"/>
    <trip id="truck_70" depart="1400.00" from="1207834766#0" to="127693103#0" type="truck__truck"/>
    <trip id="truck_71" depart="1420.00" from="1207834766#0" to="717625447#4" type="truck__truck"/>
    <trip id="truck_72" depart="1440.00" from="1198594028#0" to="1051846230#0" type="truck__truck"/>
    <trip id="truck_73" depart="1460.00" from="5672464#0" to="1198594029#0" type="truck__truck"/>
    <trip id="truck_74" depart="1480.00" from="1027189508#0" to="226041025#0" type="truck__truck"/>
    <trip id="truck_75" depart="1500.00" from="226041027#0" to="397795464#0" type="truck__truck"/>
    <trip id="truck_76" depart="1520.00" from="542257982#0" to="542258060#0" type="truck__truck"/>
    <trip id="truck_77" depart="1540.00" from="846142553#0" to="1049845754#0" type="truck__truck"/>
    <trip id="truck_78" depart="1560.00" from="1117867038#0" to="226041029#0" type="truck__truck"/>
    <trip id="truck_79" depart="1580.00" from="226041027#0" to="1320290376#0" type="truck__truck"/>
    <trip id="truck_80" depart="1600.00" from="125480075#0" to="717625447#4" type="truck__truck"/>
    <trip id="truck_81" depart="1620.00" from="384178816#0" to="569345544#0" type="truck__truck"/>
    <trip id="truck_82" depart="1640.00" from="452322756#0" to="-525729008#5" type="truck__truck"/>
    <trip id="truck_83" depart="1660.00" from="968513231#0" to="569345538#0" type="truck__truck"/>
    <trip id="truck_84" depart="1680.00" from="846142552#0" to="803047266#0" type="truck__truck"/>
    <trip id="truck_85" depart="1700.00" from="5673323#0" to="1136952921#0" type="truck__truck"/>
    <trip id="truck_86" depart="1720.00" from="420494981#0" to="125480075#0" type="truck__truck"/>
    <trip id="truck_87" depart="1740.00" from="195743209#0" to="1021047632#0" type="truck__truck"/>
    <trip id="truck_88" depart="1760.00" from="194926854#0" to="968513230#0" type="truck__truck"/>
    <trip id="truck_89" depart="1780.00" from="384178816#0" to="195743344#0" type="truck__truck"/>
    <trip id="truck_90" depart="1800.00" from="846142552#0" to="968513231#0" type="truck__truck"/>
    <trip id="truck_91" depart="1820.00" from="452322757#0" to="5670225#0" type="truck__truck"/>
    <trip id="truck_92" depart="1840.00" from="1106482765#0" to="1413518738" type="truck__truck"/>
    <trip id="truck_93" depart="1860.00" from="846142552#0" to="464516471#3" type="truck__truck"/>
    <trip id="truck_94" depart="1880.00" from="-1413518738" to="464516471#6" type="truck__truck"/>
    <trip id="truck_95" depart="1900.00" from="420907908#0" to="569345543#0" type="truck__truck"/>
    <trip id="truck_96" depart="1920.00" from="1106482765#0" to="846142553#0" type="truck__truck"/>
    <trip id="truck_97" depart="1940.00" from="-525729008#5" to="1198594029#0" type="truck__truck"/>
    <trip id="truck_98" depart="1960.00" from="569345540#0" to="1320234484#3" type="truck__truck"/>
    <trip id="truck_99" depart="1980.00" from="226041027#0" to="464516471#6" type="truck__truck"/>
    <trip id="truck_100" depart="2000.00" from="1198594026#0" to="5670225#0" type="truck__truck"/>
    <trip id="truck_101" depart="2020.00" from="167922072#0" to="5671629#0" type="truck__truck"/>
    <trip id="truck_102" depart="2040.00" from="-167922076#2" to="384178816#3" type="truck__truck"/>
    <trip id="truck_103" depart="2060.00" from="968513231#0" to="968513231#0" type="truck__truck"/>
    <trip id="truck_104" depart="2080.00" from="-167922076#2" to="125480075#0" type="truck__truck"/>
    <trip id="truck_105" depart="2100.00" from="1320234484#0" to="803047267#0" type="truck__truck"/>
    <trip id="truck_106" depart="2120.00" from="569345540#0" to="569345545#0" type="truck__truck"/>
    <trip id="truck_107" depart="2140.00" from="194926851#0" to="1117867038#0" type="truck__truck"/>
    <trip id="truck_108" depart="2160.00" from="5673323#0" to="5670225#0" type="truck__truck"/>
    <trip id="truck_109" depart="2180.00" from="464516471#13" to="968513230#0" type="truck__truck"/>
    <trip id="truck_110" depart="2200.00" from="46482609#0" to="-1321771943#1" type="truck__truck"/>
    <trip id="truck_111" depart="2220.00" from="5672464#0" to="1413518738" type="truck__truck"/>
    <trip id="truck_112" depart="2240.00" from="46522000#0" to="803047267#0" type="truck__truck"/>
    <trip id="truck_113" depart="2260.00" from="1051744070#0" to="1051745205#0" type="truck__truck"/>
    <trip id="truck_114" depart="2280.00" from="1031879418#0" to="458180183#0" type="truck__truck"/>
    <trip id="truck_115" depart="2300.00" from="542257430#0" to="1211049194#0" type="truck__truck"/>
    <trip id="truck_116" depart="2320.00" from="464516471#9" to="1320290376#0" type="truck__truck"/>
    <trip id="truck_117" depart="2340.00" from="420494981#0" to="717625447#4" type="truck__truck"/>
    <trip id="truck_118" depart="2360.00" from="5673323#0" to="1027189508#0" type="truck__truck"/>
    <trip id="truck_119" depart="2380.00" from="226041027#0" to="1320290376#0" type="truck__truck"/>
    <trip id="truck_120" depart="2400.00" from="-1136952921#1" to="5671629#0" type="truck__truck"/>
    <trip id="truck_121" depart="2420.00" from="46482609#0" to="1320290376#0" type="truck__truck"/>
    <trip id="truck_122" depart="2440.00" from="542257982#0" to="458180183#0" type="truck__truck"/>
    <trip id="truck_123" depart="2460.00" from="226041028#0" to="-1321771943#1" type="truck__truck"/>
    <trip id="truck_124" depart="2480.00" from="-167922076#2" to="569345545#0" type="truck__truck"/>
    <trip id="truck_125" depart="2500.00" from="569345543#0" to="452322757#3" type="truck__truck"/>
    <trip id="truck_126" depart="2520.00" from="5673323#0" to="464516471#6" type="truck__truck"/>
    <trip id="truck_127" depart="2540.00" from="1061622295#0" to="1051846230#0" type="truck__truck"/>
    <trip id="truck_128" depart="2560.00" from="167922070#0" to="682360554#0" type="truck__truck"/>
    <trip id="truck_129" depart="2580.00" from="5672036#0" to="569345544#0" type="truck__truck"/>
    <trip id="truck_130" depart="2600.00" from="125480075#0" to="1051744070#0" type="truck__truck"/>
    <trip id="truck_131" depart="2620.00" from="5670114#0" to="569345545#0" type="truck__truck"/>
    <trip id="truck_132" depart="2640.00" from="1106482765#0" to="803047266#0" type="truck__truck"/>
    <trip id="truck_133" depart="2660.00" from="5672464#0" to="569345545#0" type="truck__truck"/>
    <trip id="truck_134" depart="2680.00" from="-1320290376#1" to="5670867#0" type="truck__truck"/>
    <trip id="truck_135" depart="2700.00" from="167922072#0" to="803047266#0" type="truck__truck"/>
    <trip id="truck_136" depart="2720.00" from="5672036#3" to="569345545#0" type="truck__truck"/>
    <trip id="truck_137" depart="2740.00" from="5672464#0" to="1320290376#0" type="truck__truck"/>
    <trip id="truck_138" depart="2760.00" from="5670114#0" to="1051744778#0" type="truck__truck"/>
    <trip id="truck_139" depart="2780.00" from="569345540#0" to="569345544#0" type="truck__truck"/>
    <trip id="truck_140" depart="2800.00" from="1198594029#0" to="569345537#5" type="truck__truck"/>
    <trip id="truck_141" depart="2820.00" from="384178816#0" to="1413518738" type="truck__truck"/>
    <trip id="truck_142" depart="2840.00" from="5672036#0" to="1320234484#0" type="truck__truck"/>
    <trip id="truck_143" depart="2860.00" from="-1320290376#1" to="1198594030#0" type="truck__truck"/>
    <trip id="truck_144" depart="2880.00" from="167922072#0" to="569345545#0" type="truck__truck"/>
    <trip id="truck_145" depart="2900.00" from="846142552#0" to="1320290376#0" type="truck__truck"/>
    <trip id="truck_146" depart="2920.00" from="46482609#0" to="195743210" type="truck__truck"/>
    <trip id="truck_147" depart="2940.00" from="846142552#0" to="452322756#4" type="truck__truck"/>
    <trip id="truck_148" depart="2960.00" from="846142552#0" to="1198594027#0" type="truck__truck"/>
    <trip id="truck_149" depart="2980.00" from="846142552#0" to="1320290376#0" type="truck__truck"/>
    <trip id="truck_150" depart="3000.00" from="1031879418#0" to="226041027#0" type="truck__truck"/>
    <trip id="truck_151" depart="3020.00" from="542257982#0" to="1413518738" type="truck__truck"/>
    <trip id="truck_152" depart="3040.00" from="464516471#0" to="452322756#0" type="truck__truck"/>
    <trip id="truck_153" depart="3060.00" from="194926854#0" to="464516471#16" type="truck__truck"/>
    <trip id="truck_154" depart="3080.00" from="127693103#0" to="5670225#0" type="truck__truck"/>
    <trip id="truck_155" depart="3100.00" from="-1136952921#1" to="717625447#4" type="truck__truck"/>
    <trip id="truck_156" depart="3120.00" from="542257982#0" to="542258060#0" type="truck__truck"/>
    <trip id="truck_157" depart="3140.00" from="194926851#0" to="1021047632#0" type="truck__truck"/>
    <trip id="truck_158" depart="3160.00" from="46522000#0" to="167922071#0" type="truck__truck"/>
    <trip id="truck_159" depart="3180.00" from="167922071#0" to="569345540#3" type="truck__truck"/>
    <trip id="truck_160" depart="3200.00" from="542257430#0" to="1413518738" type="truck__truck"/>
    <trip id="truck_161" depart="3220.00" from="167922070#0" to="195743210" type="truck__truck"/>
    <trip id="truck_162" depart="3240.00" from="1049845754#0" to="195743344#0" type="truck__truck"/>
    <trip id="truck_163" depart="3260.00" from="1413518739#0" to="452322757#3" type="truck__truck"/>
    <trip id="truck_164" depart="3280.00" from="-1136952921#1" to="1321771943#0" type="truck__truck"/>
    <trip id="truck_165" depart="3300.00" from="226041029#0" to="464516471#3" type="truck__truck"/>
    <trip id="truck_166" depart="3320.00" from="46482609#0" to="397795463#0" type="truck__truck"/>
    <trip id="truck_167" depart="3340.00" from="384178816#0" to="125480075#0" type="truck__truck"/>
    <trip id="truck_168" depart="3360.00" from="397795463#0" to="717625447#4" type="truck__truck"/>
    <trip id="truck_169" depart="3380.00" from="5672036#0" to="1198594026#0" type="truck__truck"/>
    <trip id="truck_170" depart="3400.00" from="-542259076#2" to="452322756#4" type="truck__truck"/>
    <trip id="truck_171" depart="3420.00" from="464516471#9" to="167922073#0" type="truck__truck"/>
    <trip id="truck_172" depart="3440.00" from="5672464#0" to="5671629#0" type="truck__truck"/>
    <trip id="truck_173" depart="3460.00" from="1136952921#0" to="-1413518739#1" type="truck__truck"/>
    <trip id="truck_174" depart="3480.00" from="125480075#0" to="420494981#0" type="truck__truck"/>
    <trip id="truck_175" depart="3500.00" from="5673323#0" to="1021047632#0" type="truck__truck"/>
    <trip id="truck_176" depart="3520.00" from="1117867040#1" to="5670225#0" type="truck__truck"/>
    <trip id="truck_177" depart="3540.00" from="420907902#0" to="1320234484#3" type="truck__truck"/>
    <trip id="truck_178" depart="3560.00" from="46482609#0" to="-1321771943#1" type="truck__truck"/>
    <trip id="truck_179" depart="3580.00" from="542258337#0" to="5671629#0" type="truck__truck"/>
</routes>
